{"players": {"testplayer1": {"name": "test", "deck": "testdeck1", "elo": 1502.9135211773641}, "testplayer2": {"name": "namee", "deck": "testdeck2", "elo": 1464.5496733499808}, "p3": {"name": "eaweq", "deck": "23123", "elo": 1532.536805472655}, "string": {"name": "string", "deck": "string", "elo": 1500}}, "games": {"0": ["testplayer1", "testplayer2", 0.0, "2024-06-07T20:46:10.434313"], "1": ["testplayer2", "testplayer1", 0.0, "2024-06-07T20:57:09.386239"], "2": ["testplayer1", "p3", 0.0, "2024-06-07T21:08:45.741101"], "3": ["testplayer1", "testplayer2", 1.0, "2024-06-08T02:01:29.516170"], "4": ["testplayer1", "testplayer2", 0.5, "2024-06-08T02:01:55.879138"]}}